imapdiag/__init__.py
imapdiag/__main__.py
imapdiag/core.py
imapdiag/database.py
imapdiag/logger.py
imapdiag-0.2.dist-info/METADATA
imapdiag-0.2.dist-info/WHEEL
imapdiag-0.2.dist-info/entry_points.txt
imapdiag-0.2.dist-info/top_level.txt
imapdiag-0.2.dist-info/RECORD
