Metadata-Version: 2.1
Name: imapdiag
Version: 0.2
Summary: IMAP server diagnostics
Home-page: https://github.com/rseichter/imapdiag
Author: Ralph Seichter
Author-email: ralph.seichter@horus-it.de
License: Proprietary
Keywords: imap diagnostics
Platform: UNKNOWN
Classifier: Development Status :: 4 - Beta
Classifier: Intended Audience :: System Administrators
Classifier: License :: Other/Proprietary License
Classifier: Operating System :: OS Independent
Requires-Python: >=3.7
Requires-Dist: SQLAlchemy (>=1.1)
